otlet_cli/__init__.py
otlet_cli/__main__.py
otlet_cli/cli.py
otlet_cli/clparser/actions.py
otlet_cli/clparser/arguments.py
otlet_cli/clparser/options.py
otlet_cli/download.py
otlet_cli/util.py
otlet_cli-1.0.1.dist-info/entry_points.txt
otlet_cli-1.0.1.dist-info/LICENSE
otlet_cli-1.0.1.dist-info/WHEEL
otlet_cli-1.0.1.dist-info/METADATA
otlet_cli-1.0.1.dist-info/RECORD
