Metadata-Version: 2.1
Name: otlet-cli
Version: 1.0.1
Summary: CLI interface for otlet, the PyPI Web API wrapper
Home-page: https://github.com/nhtnr/otlet-cli
License: MIT
Author: Noah Tanner (nhtnr)
Author-email: noahtnr@gmail.com
Requires-Python: >=3.7,<4.0
Classifier: Development Status :: 5 - Production/Stable
Classifier: Intended Audience :: Developers
Classifier: License :: OSI Approved :: MIT License
Classifier: Programming Language :: Python :: 3
Classifier: Programming Language :: Python :: 3 :: Only
Classifier: Programming Language :: Python :: 3.10
Classifier: Programming Language :: Python :: 3.7
Classifier: Programming Language :: Python :: 3.8
Classifier: Programming Language :: Python :: 3.9
Requires-Dist: arrow (>=1.2.2,<2.0.0)
Requires-Dist: otlet (>=1.0.0,<2.0.0)
Project-URL: Repository, https://github.com/nhtnr/otlet-cli
